setup.cfg
setup.py
bin/hd
hd/__init__.py
hd/hd.py
hd/termsize.py
hd.egg-info/PKG-INFO
hd.egg-info/SOURCES.txt
hd.egg-info/dependency_links.txt
hd.egg-info/top_level.txt