Metadata-Version: 1.0
Name: hd
Version: 0.1.2
Summary: Hexdump library and utility.
Home-page: http://jbremer.org/
Author: Jurriaan Bremer
Author-email: jurriaanbremer@gmail.com
License: GPLv3
Platform: UNKNOWN
